MANIFEST.in
README.md
setup.py
nirjam/__init__.py
nirjam/__init__.pyc
nirjam.egg-info/PKG-INFO
nirjam.egg-info/SOURCES.txt
nirjam.egg-info/dependency_links.txt
nirjam.egg-info/not-zip-safe
nirjam.egg-info/requires.txt
nirjam.egg-info/top_level.txt
nirjam/traffic/__init__.py
nirjam/traffic/__init__.pyc
nirjam/traffic/network.py
nirjam/traffic/network.pyc
nirjam/traffic/nirjam-0.1.1.tar.gz
nirjam/ultrasonic/__init__.py
nirjam/ultrasonic/__init__.pyc