Metadata-Version: 1.0
Name: nirjam
Version: 0.1.3
Summary: A mixture features for the Raspberry Pi
Home-page: http://github.com/vlee489/nirjam
Author: vlee489
Author-email: vlee@vlee.me.uk
License: MIT
Platform: UNKNOWN
